{
    "/js/app.js": "/js/app.js",
    "/js/user.js": "/js/user.js",
    "/js/inventory.js": "/js/inventory.js",
    "/js/qr-code.js": "/js/qr-code.js",
    "/js/qr-scanner.js": "/js/qr-scanner.js",
    "/js/qr-backend-handler.js": "/js/qr-backend-handler.js",
    "/js/print-receipt.js": "/js/print-receipt.js",
    "/js/sales-qr-scanner.js": "/js/sales-qr-scanner.js",
    "/js/sales-form.js": "/js/sales-form.js",
    "/js/sales-page.js": "/js/sales-page.js",
    "/js/remote-sales-scanner.js": "/js/remote-sales-scanner.js",
    "/js/remote-sales-phone-scanner.js": "/js/remote-sales-phone-scanner.js",
    "/css/filter-layout.css": "/css/filter-layout.css",
    "/css/admin.css": "/css/admin.css",
    "/css/app.css": "/css/app.css"
}
